{
	"name": "Ingestion",
	"properties": {
		"activities": [
			{
				"name": "last CDC",
				"type": "Lookup",
				"dependsOn": [],
				"policy": {
					"timeout": "0.12:00:00",
					"retry": 0,
					"retryIntervalInSeconds": 30,
					"secureOutput": false,
					"secureInput": false
				},
				"userProperties": [],
				"typeProperties": {
					"source": {
						"type": "JsonSource",
						"storeSettings": {
							"type": "AzureBlobFSReadSettings",
							"recursive": true,
							"enablePartitionDiscovery": false
						},
						"formatSettings": {
							"type": "JsonReadSettings"
						}
					},
					"dataset": {
						"referenceName": "ds_cdc",
						"type": "DatasetReference"
					},
					"firstRowOnly": false
				}
			},
			{
				"name": "Total_Results",
				"type": "Script",
				"dependsOn": [
					{
						"activity": "last CDC",
						"dependencyConditions": [
							"Succeeded"
						]
					}
				],
				"policy": {
					"timeout": "0.12:00:00",
					"retry": 3,
					"retryIntervalInSeconds": 60,
					"secureOutput": false,
					"secureInput": false
				},
				"userProperties": [],
				"linkedServiceName": {
					"referenceName": "ls_database",
					"type": "LinkedServiceReference"
				},
				"typeProperties": {
					"scripts": [
						{
							"type": "Query",
							"text": {
								"value": "select count(*) as total_count from @{pipeline().parameters.schemaname}.@{pipeline().parameters.tablename} where last_updated > '@{if(empty(pipeline().parameters.backdate),\n    activity('last CDC').output.value[0].cdc_timestamp,pipeline().parameters.backdate)}'",
								"type": "Expression"
							}
						}
					],
					"scriptBlockExecutionTimeout": "02:00:00"
				}
			},
			{
				"name": "If Condition1",
				"type": "IfCondition",
				"dependsOn": [
					{
						"activity": "Total_Results",
						"dependencyConditions": [
							"Succeeded"
						]
					}
				],
				"userProperties": [],
				"typeProperties": {
					"expression": {
						"value": "@greater(activity('Total_Results').output.resultSets[0].rows[0].total_count,0 )",
						"type": "Expression"
					},
					"ifTrueActivities": [
						{
							"name": "Load",
							"type": "Copy",
							"dependsOn": [],
							"policy": {
								"timeout": "0.00:30:00",
								"retry": 3,
								"retryIntervalInSeconds": 48,
								"secureOutput": false,
								"secureInput": false
							},
							"userProperties": [],
							"typeProperties": {
								"source": {
									"type": "AzureSqlSource",
									"sqlReaderQuery": {
										"value": "select * from @{pipeline().parameters.schemaname}.@{pipeline().parameters.tablename} where last_updated > '@{if(empty(pipeline().parameters.backdate),\n    activity('last CDC').output.value[0].cdc_timestamp,pipeline().parameters.backdate)}'",
										"type": "Expression"
									},
									"queryTimeout": "02:00:00",
									"partitionOption": "None"
								},
								"sink": {
									"type": "ParquetSink",
									"storeSettings": {
										"type": "AzureBlobFSWriteSettings"
									},
									"formatSettings": {
										"type": "ParquetWriteSettings"
									}
								},
								"enableStaging": false,
								"translator": {
									"type": "TabularTranslator",
									"typeConversion": true,
									"typeConversionSettings": {
										"allowDataTruncation": true,
										"treatBooleanAsNumber": false
									}
								}
							},
							"inputs": [
								{
									"referenceName": "ds_database",
									"type": "DatasetReference"
								}
							],
							"outputs": [
								{
									"referenceName": "ds_parquet",
									"type": "DatasetReference"
								}
							]
						},
						{
							"name": "change cdc",
							"type": "Copy",
							"dependsOn": [
								{
									"activity": "max CDC",
									"dependencyConditions": [
										"Succeeded"
									]
								}
							],
							"policy": {
								"timeout": "0.12:00:00",
								"retry": 0,
								"retryIntervalInSeconds": 30,
								"secureOutput": false,
								"secureInput": false
							},
							"userProperties": [],
							"typeProperties": {
								"source": {
									"type": "JsonSource",
									"additionalColumns": [
										{
											"name": "cdc_timestamp",
											"value": {
												"value": "@activity('max CDC').output.resultSets[0].rows[0].cdc_timestamp",
												"type": "Expression"
											}
										}
									],
									"storeSettings": {
										"type": "AzureBlobFSReadSettings",
										"recursive": true,
										"enablePartitionDiscovery": false
									},
									"formatSettings": {
										"type": "JsonReadSettings"
									}
								},
								"sink": {
									"type": "JsonSink",
									"storeSettings": {
										"type": "AzureBlobFSWriteSettings"
									},
									"formatSettings": {
										"type": "JsonWriteSettings"
									}
								},
								"enableStaging": false
							},
							"inputs": [
								{
									"referenceName": "ds_emptyjson",
									"type": "DatasetReference"
								}
							],
							"outputs": [
								{
									"referenceName": "ds_cdc",
									"type": "DatasetReference"
								}
							]
						},
						{
							"name": "max CDC",
							"type": "Script",
							"dependsOn": [
								{
									"activity": "Load",
									"dependencyConditions": [
										"Succeeded"
									]
								}
							],
							"policy": {
								"timeout": "0.12:00:00",
								"retry": 0,
								"retryIntervalInSeconds": 30,
								"secureOutput": false,
								"secureInput": false
							},
							"userProperties": [],
							"linkedServiceName": {
								"referenceName": "ls_database",
								"type": "LinkedServiceReference"
							},
							"typeProperties": {
								"scripts": [
									{
										"type": "Query",
										"text": {
											"value": "select max(last_updated) as cdc_timestamp from @{pipeline().parameters.schemaname}.@{pipeline().parameters.tablename}",
											"type": "Expression"
										}
									}
								],
								"scriptBlockExecutionTimeout": "02:00:00"
							}
						}
					]
				}
			}
		],
		"parameters": {
			"schemaname": {
				"type": "string",
				"defaultValue": "source"
			},
			"tablename": {
				"type": "string",
				"defaultValue": "Orders"
			},
			"backdate": {
				"type": "string",
				"defaultValue": "2025-09-24"
			}
		},
		"variables": {
			"test": {
				"type": "String"
			}
		},
		"annotations": [],
		"lastPublishTime": "2026-04-21T11:50:35Z"
	},
	"type": "Microsoft.DataFactory/factories/pipelines"
}